README.rst
setup.py
utl/__init__.py
utl/utl.py
utl.egg-info/PKG-INFO
utl.egg-info/SOURCES.txt
utl.egg-info/dependency_links.txt
utl.egg-info/entry_points.txt
utl.egg-info/requires.txt
utl.egg-info/top_level.txt