Metadata-Version: 1.1
Name: utl
Version: 1.0.1
Summary: A simple tool that shows available tests without executing
Home-page: UNKNOWN
Author: xliiv
Author-email: tymoteusz.jankowski@gmail.com
License: UNKNOWN
Platform: UNKNOWN
Classifier: Development Status :: 4 - Beta
Classifier: Programming Language :: Python
Classifier: Programming Language :: Python :: 2
Classifier: Programming Language :: Python :: 2.7
Classifier: Programming Language :: Python :: 3
Classifier: Programming Language :: Python :: 3.3
Classifier: Topic :: Software Development :: Testing
